op_aws_vault/__init__.py
op_aws_vault-0.0.9.dist-info/METADATA
op_aws_vault-0.0.9.dist-info/WHEEL
op_aws_vault-0.0.9.dist-info/entry_points.txt
op_aws_vault-0.0.9.dist-info/licenses/LICENSE
op_aws_vault-0.0.9.dist-info/RECORD
