Metadata-Version: 2.4
Name: op-aws-vault
Version: 0.0.9
Summary: 1Password aws-vault like utility
Project-URL: Homepage, https://github.com/dmarkey/op-aws-vault
Project-URL: Bug Tracker, https://github.com/dmarkey/op-aws-vault/issues
Author-email: David Markey <david@dmarkey.com>
License-File: LICENSE
Requires-Python: >=3.8
Requires-Dist: boto3
Requires-Dist: pytimeparse2
Requires-Dist: requests
Requires-Dist: typer
